lotr_sdk/__init__.py
lotr_sdk/api_methods.py
lotr_sdk/conf.py
lotr_sdk/movies.py
lotr_sdk/quotes.py
tests/__init__.py
tests/test.py
dr_lord_of_the_rings_sdk-0.0.3.dist-info/LICENCE.txt
dr_lord_of_the_rings_sdk-0.0.3.dist-info/METADATA
dr_lord_of_the_rings_sdk-0.0.3.dist-info/WHEEL
dr_lord_of_the_rings_sdk-0.0.3.dist-info/top_level.txt
dr_lord_of_the_rings_sdk-0.0.3.dist-info/RECORD
