Metadata-Version: 2.1
Name: dr-lord-of-the-rings-sdk
Version: 0.0.3
Summary: SDK for interacting with the Lord of the Rings API
Home-page: https://github.com/DannyBuffet/Lord-of-the-rings-sdk
Author: Daniel Reliford
Author-email: dreliford@gmail.com
Classifier: Development Status :: 3 - Alpha
Classifier: Intended Audience :: Developers
Classifier: License :: OSI Approved :: MIT License
Classifier: Programming Language :: Python :: 3
Classifier: Programming Language :: Python :: 3.6
Classifier: Programming Language :: Python :: 3.7
Classifier: Programming Language :: Python :: 3.8
Classifier: Programming Language :: Python :: 3.9
Classifier: Programming Language :: Python :: 3 :: Only
Classifier: Topic :: Software Development :: Libraries
Classifier: Topic :: Software Development :: Libraries :: Python Modules
Requires-Python: >=3.6
License-File: LICENCE.txt
Requires-Dist: requests
